[
  {
    "name": "Convergence",
    "decoded": "7, 0, 1, 50| 2, 3308|| {100} {2} {6} {3} {4} {64} {74} {70} {15} {28} {36} {35} {42} {50}|"
  },
  {
    "name": "Convergence",
    "decoded": "7, 0, 1, 50| 2, 3308|| {100} {2} {6} {3} {4} {1:14} {64} {74} {70} {15} {28} {36} {35} {42} {50}|"
  },
  {
    "name": "Bod",
    "decoded": "8, 0, 1, 50| 2, 1531|| {53} {2} {6} {1:11} {52} {74} {11} {15} {76} {26} {31} {30} {39} {49} {80}|"
  },
  {
    "name": "Convergence",
    "decoded": "7, 0, 1, 50| 2, 1332|| {100} {2} {4} {5} {6} {1:11} {64} {74} {70} {15} {26} {38} {37} {43} {51}|"
  },
  {
    "name": "Convergence",
    "decoded": "7, 0, 1, 50| 2, 3308|| {100} {2} {6} {3} {4} {1:12} {64} {74} {70} {15} {28} {36} {35} {42} {50}|"
  },
  {
    "name": "Convergence",
    "decoded": "7, 0, 1, 50| 2, 3308|| {100} {2} {6} {3} {4} {1:13} {64} {74} {70} {15} {28} {36} {35} {42} {50}|"
  },
  {
    "name": "Convergence",
    "decoded": "7, 0, 1, 50| 2, 3308|| {100} {2} {6} {3} {4} {1:10} {64} {74} {70} {15} {28} {36} {35} {42} {50}|"
  },
  {
    "name": "Kaoson",
    "decoded": "22, 0, 1, 50| 2, 424|| {67} {2} {6} {3} {1:14} {66} {72} {73} {15} {19} {25} {28} {35} {44} {48} {59}|"
  },
  {
    "name": "Bod",
    "decoded": "8, 0, 1, 50| 2, 1232|| {53} {2} {3} {4} {52} {74} {12} {15} {75} {24} {29} {28} {39} {47} {78}|"
  },
  {
    "name": "Kaoson",
    "decoded": "22, 0, 1, 50| 2, 424|| {67} {2} {6} {3} {1:11} {66} {72} {73} {15} {19} {25} {28} {35} {44} {48} {59}|"
  },
  {
    "name": "Kaoson",
    "decoded": "22, 0, 1, 50| 2, 424|| {67} {2} {6} {3} {1:12} {66} {72} {73} {15} {19} {25} {28} {35} {44} {48} {59}|"
  },
  {
    "name": "T.K's Wave",
    "decoded": "9, 0, 1, 50| 2, 3061|| {91} {2} {3} {6} {90} {59} {61} {62} {15} {89} {24} {28} {29} {40} {44}|"
  },
  {
    "name": "Bod",
    "decoded": "8, 0, 1, 50| 2, 1232|| {53} {2} {3} {4} {52} {74} {12} {15} {76} {24} {29} {28} {39} {47} {78}|"
  },
  {
    "name": "Katagawa's Revenge",
    "decoded": "25, 0, 1, 50| 2, 3526|| {61} {2} {4} {5} {3} {1:12} {60} {69} {73} {71} {70} {13} {27} {32} {31} {43} {52} {1:48}|"
  },
  {
    "name": "Rainbow Vomit",
    "decoded": "9, 0, 1, 50| 2, 3392|| {85} {2} {6} {84} {86} {56} {55} {58} {87} {25} {32} {33} {40} {45}|"
  },
  {
    "name": "T.K's Wave",
    "decoded": "9, 0, 1, 50| 2, 3061|| {91} {2} {3} {6} {90} {59} {61} {62} {15} {89} {24} {28} {29} {40} {45}|"
  },
  {
    "name": "Boory",
    "decoded": "22, 0, 1, 50| 2, 1338|| {98} {2} {3} {4} {5} {7} {80} {72} {74} {75} {15} {18} {29} {33} {34} {45} {53} {58}|"
  },
  {
    "name": "Boory",
    "decoded": "22, 0, 1, 50| 2, 1340|| {98} {2} {3} {4} {5} {1:11} {7} {80} {72} {74} {75} {15} {18} {29} {33} {34} {45} {53} {58}|"
  },
  {
    "name": "Boory",
    "decoded": "22, 0, 1, 50| 2, 1342|| {98} {2} {3} {4} {5} {1:13} {7} {80} {72} {74} {75} {15} {18} {29} {33} {34} {45} {53} {58}|"
  },
  {
    "name": "Birt's Bees",
    "decoded": "22, 0, 1, 50| 2, 3531|| {88} {2} {5} {87} {80} {15} {71} {25} {28} {36} {35} {46} {52}|"
  },
  {
    "name": "Wombo Combo",
    "decoded": "18, 0, 1, 50| 2, 2083|| {65} {2} {3} {4} {1:13} {64} {72} {14} {27} {35} {34} {41} {58}|"
  },
  {
    "name": "Wombo Combo",
    "decoded": "18, 0, 1, 50| 2, 3575|| {65} {2} {4} {3} {1:11} {64} {72} {14} {27} {34} {35} {41} {58}|"
  },
  {
    "name": "Bod",
    "decoded": "8, 0, 1, 50| 2, 2495|| {53} {2} {5} {6} {1:12} {52} {74} {11} {15} {76} {26} {30} {41} {47} {77}|"
  },
  {
    "name": "Wombo Combo",
    "decoded": "18, 0, 1, 50| 2, 3264|| {65} {2} {4} {3} {1:12} {64} {72} {14} {27} {35} {34} {41} {58}|"
  },
  {
    "name": "Wombo Combo",
    "decoded": "18, 0, 1, 50| 2, 1825|| {65} {2} {3} {4} {1:10} {64} {72} {14} {27} {35} {34} {41} {58}|"
  },
  {
    "name": "Wombo Combo",
    "decoded": "18, 0, 1, 50| 2, 1136|| {65} {2} {3} {4} {1:14} {64} {72} {14} {27} {34} {35} {41} {58}|"
  },
  {
    "name": "Lucian's Flank",
    "decoded": "18, 0, 1, 50| 2, 1994|| {63} {2} {5} {1:11} {1} {72} {74} {80} {14} {26} {30} {31} {41} {86} {53} {66}|"
  },
  {
    "name": "Lucian's Flank",
    "decoded": "18, 0, 1, 50| 2, 289|| {63} {2} {5} {3} {1:13} {1} {74} {80} {72} {13} {26} {30} {41} {86} {67}|"
  },
  {
    "name": "Lucian's Flank",
    "decoded": "18, 0, 1, 50| 2, 1516|| {63} {2} {3} {1:14} {1} {72} {74} {80} {14} {26} {30} {31} {41} {86} {66}|"
  },
  {
    "name": "Lucian's Flank",
    "decoded": "18, 0, 1, 50| 2, 2317|| {63} {2} {4} {1:10} {1} {80} {74} {72} {13} {26} {30} {31} {41} {86} {67}|"
  },
  {
    "name": "Lucian's Flank",
    "decoded": "18, 0, 1, 50| 2, 3270|| {63} {2} {4} {1:12} {1} {74} {72} {80} {14} {26} {30} {31} {41} {86} {66}|"
  },
  {
    "name": "Whiskey Foxtrot",
    "decoded": "18, 0, 1, 50| 2, 174|| {93} {2} {4} {3} {94} {76} {80} {17} {26} {31} {30} {42} {90} {56}|"
  },
  {
    "name": "Oscar Mike",
    "decoded": "13, 0, 1, 50| 2, 2965|| {100} {1} {4} {8} {17} {11} {9} {26} {29} {36} {40} {42} {43} {53} {75}|"
  },
  {
    "name": "Oscar Mike",
    "decoded": "13, 0, 1, 50| 2, 1051|| {100} {1} {3} {2} {8} {1:11} {10} {9} {23} {81} {26} {32} {36} {39} {45} {44} {55} {75}|"
  },
  {
    "name": "Oscar Mike",
    "decoded": "13, 0, 1, 50| 2, 1051|| {100} {1} {3} {2} {8} {10} {9} {23} {81} {26} {32} {36} {39} {45} {44} {55} {75}|"
  },
  {
    "name": "Oscar Mike",
    "decoded": "13, 0, 1, 50| 2, 1051|| {100} {1} {3} {2} {8} {1:12} {10} {9} {23} {81} {26} {32} {36} {39} {45} {44} {55} {75}|"
  },
  {
    "name": "Oscar Mike",
    "decoded": "13, 0, 1, 50| 2, 1051|| {100} {1} {3} {2} {8} {1:10} {10} {9} {23} {81} {26} {32} {36} {39} {45} {44} {55} {75}|"
  },
  {
    "name": "Seventh Sense",
    "decoded": "3, 0, 1, 50| 2, 1883|| {81} {2} {3} {5} {4} {6} {80} {51} {52} {53} {13} {26} {31} {30} {41} {47} {65}|"
  },
  {
    "name": "Seventh Sense",
    "decoded": "3, 0, 1, 50| 2, 3612|| {81} {2} {3} {4} {6} {5} {80} {54} {52} {53} {51} {13} {26} {30} {31} {41} {70}|"
  },
  {
    "name": "Seventh Sense",
    "decoded": "3, 0, 1, 50| 2, 402|| {81} {2} {3} {6} {4} {80} {52} {53} {51} {54} {13} {26} {30} {31} {41} {47} {67}|"
  },
  {
    "name": "Phantom Flame",
    "decoded": "3, 0, 1, 50| 2, 1937|| {78} {2} {4} {3} {5} {6} {77} {51} {53} {52} {54} {14} {25} {41} {70}|"
  },
  {
    "name": "Finnity XXX-L",
    "decoded": "16, 0, 1, 50| 2, 3887|| {66} {2} {5} {4} {1:12} {1} {77} {80} {16} {26} {42} {59}|"
  },
  {
    "name": "Complex Root",
    "decoded": "25, 0, 1, 50| 2, 881|| {59} {2} {5} {6} {4} {3} {1:12} {20} {73} {67} {65} {66} {13} {28} {36} {35} {43} {54}|"
  },
  {
    "name": "Complex Root",
    "decoded": "25, 0, 1, 50| 2, 2335|| {59} {2} {5} {4} {3} {6} {1:11} {20} {73} {67} {65} {66} {13} {28} {36} {35} {43} {54}|"
  },
  {
    "name": "Complex Root",
    "decoded": "25, 0, 1, 50| 2, 2950|| {59} {2} {6} {3} {5} {4} {1:13} {20} {73} {67} {65} {66} {13} {28} {36} {35} {43} {54}|"
  },
  {
    "name": "Complex Root",
    "decoded": "25, 0, 1, 50| 2, 90|| {59} {2} {4} {6} {3} {5} {1:10} {20} {67} {73} {66} {65} {13} {28} {36} {35} {43} {54}|"
  },
  {
    "name": "Complex Root",
    "decoded": "25, 0, 1, 50| 2, 3246|| {59} {2} {5} {4} {6} {3} {1:14} {20} {73} {67} {65} {66} {13} {28} {36} {35} {43} {54}|"
  },
  {
    "name": "Stray",
    "decoded": "23, 0, 1, 50| 2, 1855|| {19} {2} {3} {4} {20} {74} {66} {68} {14} {27} {32} {31} {43} {52}|"
  },
  {
    "name": "Stray",
    "decoded": "23, 0, 1, 50| 2, 1423|| {19} {2} {6} {4} {1:13} {20} {67} {74} {66} {14} {30} {38} {45} {53} {62}|"
  },
  {
    "name": "Hot Slugger",
    "decoded": "9, 0, 1, 50| 2, 2899|| {80} {2} {79} {78} {23} {40} {68}|"
  },
  {
    "name": "Stray",
    "decoded": "23, 0, 1, 50| 2, 1423|| {19} {2} {6} {4} {1:11} {20} {67} {74} {66} {14} {30} {38} {45} {53} {62}|"
  },
  {
    "name": "Midnight Defiance",
    "decoded": "16, 0, 1, 50| 2, 2859|| {69} {2} {4} {5} {68} {73} {75} {25} {14} {30} {37} {38} {42} {46} {60} {62}|"
  },
  {
    "name": "Midnight Defiance",
    "decoded": "16, 0, 1, 50| 2, 992|| {69} {2} {6} {4} {68} {75} {76} {25} {16} {27} {32} {31} {43} {50} {55} {61}|"
  },
  {
    "name": "Rainbow Vomit",
    "decoded": "9, 0, 1, 50| 2, 725|| {85} {2} {3} {6} {72} {86} {55} {56} {87} {24} {28} {40} {45}|"
  },
  {
    "name": "Dullahan",
    "decoded": "9, 0, 1, 50| 2, 563|| {98} {2} {5} {4} {6} {7} {67} {55} {56} {10} {93} {24} {29} {28} {40} {45}|"
  },
  {
    "name": "Stellium",
    "decoded": "10, 0, 1, 50| 2, 861|| {98} {2} {5} {4} {6} {1:11} {8} {66} {63} {65} {79} {77} {25} {33} {32} {40} {43}|"
  },
  {
    "name": "Stellium",
    "decoded": "10, 0, 1, 50| 2, 861|| {98} {2} {5} {4} {6} {1:13} {8} {66} {63} {65} {79} {77} {25} {33} {32} {40} {43}|"
  },
  {
    "name": "Stellium",
    "decoded": "10, 0, 1, 50| 2, 861|| {98} {2} {5} {4} {6} {1:10} {8} {66} {63} {65} {79} {77} {25} {33} {32} {40} {43}|"
  },
  {
    "name": "Stellium",
    "decoded": "10, 0, 1, 50| 2, 861|| {98} {2} {5} {4} {6} {1:14} {8} {66} {63} {65} {79} {77} {25} {33} {32} {40} {43}|"
  },
  {
    "name": "Stellium",
    "decoded": "10, 0, 1, 50| 2, 861|| {98} {2} {5} {4} {6} {1:12} {8} {66} {63} {65} {79} {77} {25} {33} {32} {40} {43}|"
  },
  {
    "name": "Kickballer",
    "decoded": "10, 0, 1, 50| 2, 3354|| {100} {2} {6} {1:13} {7} {71} {63} {16} {24} {29} {41} {44}|"
  },
  {
    "name": "Unknown",
    "decoded": "300, 0, 1, 50| 9, 1| 2, 3471|| {9} {8} {246:26} {248:[17 16]} {246:1}|"
  },
  {
    "name": "Unknown",
    "decoded": "300, 0, 1, 50| 9, 1| 10, 1| 2, 1155|| {9} {8} {246:26} {248:[17 6]} {246:5}|"
  },
  {
    "name": "Unknown",
    "decoded": "292, 0, 1, 50| 2, 1741|| {5} {247:79} {1} {247:90}|"
  },
  {
    "name": "Unknown",
    "decoded": "278, 0, 1, 50| 2, 3894|| {5} {2} {245:[25 76]}|"
  },
  {
    "name": "Unknown",
    "decoded": "279, 0, 1, 49| 2, 1179|| {4} {2} {246:[26 37]}|"
  },
  {
    "name": "Unknown",
    "decoded": "321, 0, 1, 49| 2, 2372|| {1} {10}|"
  },
  {
    "name": "Unknown",
    "decoded": "254, 0, 1, 49| 2, 1343|| {218} {9} {190} {158} {126} {275} {234:45}|"
  },
  {
    "name": "Buzzymuzz",
    "decoded": "18, 0, 1, 50| 2, 3473|| {98} {2} {5} {6} {3} {1:12} {7} {75} {73} {74} {13} {26} {30} {31} {41} {85} {56} {1:30}|"
  },
  {
    "name": "Lemma",
    "decoded": "4, 0, 1, 50| 2, 2651|| {96} {2} {6} {5} {8} {59} {14} {25} {29} {39} {48}|"
  },
  {
    "name": "Unknown",
    "decoded": "296, 0, 1, 50| 2, 1619|| {6} {247:77} {2} {247:[56 211 162]}|"
  },
  {
    "name": "Unknown",
    "decoded": "287, 0, 1, 50| 2, 231|| {2} {10} {246:[23 31]}|"
  },
  {
    "name": "Unknown",
    "decoded": "255, 0, 1, 50| 2, 2975|| {68} {8} {37} {247} {227} {107} {255} {234:[24 44]}|"
  },
  {
    "name": "Unknown",
    "decoded": "287, 0, 1, 50| 2, 1707|| {4} {10} {246:22} {237:25} {246:49}|"
  },
  {
    "name": "Unknown",
    "decoded": "286, 0, 1, 50| 2, 3103|| {7} {247:79} {9} {247:88}|"
  },
  {
    "name": "Unknown",
    "decoded": "292, 0, 1, 50| 2, 2389|| {4} {247:80} {1}|"
  },
  {
    "name": "Unknown",
    "decoded": "256, 0, 1, 50| 2, 186|| {67} {6} {280} {50} {57} {93} {234:34}|"
  },
  {
    "name": "Unknown",
    "decoded": "256, 0, 1, 50| 2, 3738|| {67} {3} {272} {45} {335} {398} {234:28}|"
  },
  {
    "name": "Unknown",
    "decoded": "256, 0, 1, 50| 2, 2133|| {68} {3} {275} {45} {89} {338} {401} {234:[102 11]}|"
  },
  {
    "name": "Unknown",
    "decoded": "285, 0, 1, 50| 2, 3584|| {6} {2} {243:[105 98 56 77 11]}|"
  },
  {
    "name": "Unknown",
    "decoded": "279, 0, 1, 50| 2, 2030|| {4} {2} {246:[25 37]}|"
  }
]